LICENSE.txt
MANIFEST.in
README.md
setup.cfg
setup.py
traffic_light_simulator_demo/__init__.py
traffic_light_simulator_demo/helpers.py
traffic_light_simulator_demo/test.py
traffic_light_simulator_demo/traffic_light.py
traffic_light_simulator_demo/user_interface.py
traffic_light_simulator_demo.egg-info/PKG-INFO
traffic_light_simulator_demo.egg-info/SOURCES.txt
traffic_light_simulator_demo.egg-info/dependency_links.txt
traffic_light_simulator_demo.egg-info/entry_points.txt
traffic_light_simulator_demo.egg-info/top_level.txt
traffic_light_simulator_demo/traffic_light_art/green.txt
traffic_light_simulator_demo/traffic_light_art/red.txt
traffic_light_simulator_demo/traffic_light_art/yellow.txt