Metadata-Version: 2.1
Name: traffic-light-simulator-demo
Version: 0.10
Summary: traffic light simulator
Home-page: https://github.com/ydotzh/Traffic_Light_Simulator
Download-URL: https://github.com/ydotzh/Traffic_Light_Simulator/archive/refs/tags/v_02.tar.gz
Author: Yan
Author-email: yzhao1990@gmail.com
License: MIT
Keywords: Data Challenge
License-File: LICENSE.txt
